.gitignore
setup.py
examples/__init__.py
examples/config.json
examples/messages.py
examples/jobs/__init__.py
examples/jobs/test_job1.py
examples/jobs/test_job2.py
nico/__init__.py
nico/consts.py
nico/consumer.py
nico/kafka_client.py
nico/load_settings.py
nico/main.py
nico/register.py
nico/utils.py
nico.egg-info/PKG-INFO
nico.egg-info/SOURCES.txt
nico.egg-info/dependency_links.txt
nico.egg-info/entry_points.txt
nico.egg-info/requires.txt
nico.egg-info/top_level.txt