Metadata-Version: 1.0
Name: nico
Version: 0.1
Summary: job scheduler for kafka message
Home-page: https://github.com/omsobliga
Author: omsobliga
Author-email: omsobliga@gmail.com
License: MIT
Platform: UNKNOWN
